hyjinx/__init__.py
hyjinx/actors.hy
hyjinx/crypto.hy
hyjinx/docs.hy
hyjinx/duck.hy
hyjinx/hjx_inspect.py
hyjinx/hyrc.hy
hyjinx/labs.hy
hyjinx/lib.hy
hyjinx/llm.hy
hyjinx/macros.hy
hyjinx/mail.hy
hyjinx/mat.hy
hyjinx/screen.hy
hyjinx/serialize.py
hyjinx/source.hy
hyjinx/wire.hy
hyjinx/zmq_client.hy
hyjinx/zmq_server.hy
hyjinx-1.2.1.dist-info/licenses/AUTHORS
hyjinx-1.2.1.dist-info/licenses/LICENSE
hyjinx-1.2.1.dist-info/METADATA
hyjinx-1.2.1.dist-info/WHEEL
hyjinx-1.2.1.dist-info/top_level.txt
hyjinx-1.2.1.dist-info/RECORD
