Metadata-Version: 2.4
Name: hyjinx
Version: 1.2.1
Summary: A minimal Hy utility library, using mostly the standard libraries.
Author-email: Ati Sharma <ati+hyjinx@agalmic.ltd>
License: MIT License
Project-URL: Repository, https://github.com/atisharma/hyjinx
Keywords: hy,hylang,utilities,zeromq,llm,openai,anthropic
Classifier: License :: OSI Approved :: MIT License
Classifier: Programming Language :: Python :: 3
Classifier: Programming Language :: Python :: 3.13
Classifier: Programming Language :: Python :: 3.14
Classifier: Programming Language :: Lisp
Classifier: Programming Language :: Hy
Classifier: Topic :: Software Development :: Libraries
Classifier: Topic :: Utilities
Requires-Python: >=3.13
License-File: LICENSE
License-File: AUTHORS
Requires-Dist: ansi-escapes
Requires-Dist: beautifhy>=1.1.4
Requires-Dist: colorist
Requires-Dist: hy>=1.2.0
Requires-Dist: hyrule
Requires-Dist: json-repair
Requires-Dist: more-itertools
Requires-Dist: multimethod
Requires-Dist: platformdirs
Requires-Dist: python-magic
Requires-Dist: toolz
Provides-Extra: zmq
Requires-Dist: ecdsa; extra == "zmq"
Requires-Dist: pyzmq; extra == "zmq"
Requires-Dist: zstandard; extra == "zmq"
Requires-Dist: msgpack; extra == "zmq"
Provides-Extra: llm
Requires-Dist: openai; extra == "llm"
Requires-Dist: anthropic; extra == "llm"
Provides-Extra: dev
Requires-Dist: pytest; extra == "dev"
Requires-Dist: ecdsa; extra == "dev"
Requires-Dist: pyzmq; extra == "dev"
Requires-Dist: zstandard; extra == "dev"
Requires-Dist: msgpack; extra == "dev"
Requires-Dist: openai; extra == "dev"
Requires-Dist: anthropic; extra == "dev"
Dynamic: license-file
